{
  "name": "Emacs",
  "bindings": {
    "File.New": "Ctrl+X, Ctrl+N",
    "File.Open": "Ctrl+X, Ctrl+F",
    "File.Save": "Ctrl+X, Ctrl+S",
    "File.SaveAs": "Ctrl+X, Ctrl+W",
    "File.SaveAll": "",
    "File.RevertFile": "",
    "File.Print": "",
    "File.SaveAsPdf": "",
    "File.Close": "Ctrl+X, Ctrl+K",
    "File.CloseAll": "",
    "File.Exit": "Ctrl+X, Ctrl+C",
    "File.ToggleReadOnly": "",
    "File.ReloadFile": "",
    "File.ClearRecentFiles": "",
    "Edit.Undo": "Ctrl+Z",
    "Edit.Redo": "Ctrl+Shift+Z",
    "Edit.Cut": "Ctrl+W",
    "Edit.Copy": "Alt+W",
    "Edit.Paste": "Ctrl+Y",
    "Edit.PasteMore": "Ctrl+Shift+V",
    "Edit.ClipboardRing": "",
    "Edit.Delete": "Delete",
    "Edit.SelectAll": "Ctrl+X, Ctrl+A",
    "Edit.SelectWord": "",
    "Edit.DeleteLine": "Ctrl+K",
    "Edit.MoveLineUp": "Alt+Up",
    "Edit.MoveLineDown": "Alt+Down",
    "Edit.InsertLineBelow": "",
    "Edit.InsertLineAbove": "",
    "Edit.DuplicateLine": "",
    "Edit.DeleteWordLeft": "Alt+Back",
    "Edit.DeleteWordRight": "Alt+D",
    "Edit.SmartIndent": "Tab",
    "Edit.UpperCase": "Ctrl+Shift+U",
    "Edit.LowerCase": "Ctrl+Shift+L",
    "Edit.ProperCase": "Ctrl+Shift+P",
    "Edit.Backspace": "Back",
    "Edit.Newline": "Return",
    "Edit.Tab": "",
    "Edit.ToggleOverwrite": "Insert",
    "Edit.ExpandSelection": "",
    "Edit.Indent": "",
    "Edit.Outdent": "Shift+Tab",
    "Edit.IndentToSpaces": "",
    "Edit.IndentToTabs": "",
    "Search.Find": "",
    "Search.Replace": "",
    "Search.FindNext": "",
    "Search.FindPrevious": "",
    "Search.FindNextSelection": "",
    "Search.FindPreviousSelection": "",
    "Search.IncrementalSearch": "",
    "View.LineNumbers": "",
    "View.StatusBar": "",
    "View.WrapLines": "",
    "View.Whitespace": "",
    "View.ZoomIn": "",
    "View.ZoomOut": "",
    "View.ZoomReset": "Ctrl+D0",
    "View.ScrollLineUp": "Ctrl+Up",
    "View.ScrollLineDown": "Ctrl+Down",
    "Search.GoToLine": "",
    "Nav.FocusEditor": "",
    "Nav.MoveLeft": "Left",
    "Nav.SelectLeft": "Shift+Left",
    "Nav.MoveRight": "Right",
    "Nav.SelectRight": "Shift+Right",
    "Nav.MoveWordLeft": "Ctrl+Left",
    "Nav.SelectWordLeft": "Ctrl+Shift+Left",
    "Nav.MoveWordRight": "Ctrl+Right",
    "Nav.SelectWordRight": "Ctrl+Shift+Right",
    "Nav.MoveUp": "Up",
    "Nav.SelectUp": "Shift+Up",
    "Nav.MoveDown": "Down",
    "Nav.SelectDown": "Shift+Down",
    "Nav.MoveHome": "Home",
    "Nav.SelectHome": "Shift+Home",
    "Nav.MoveEnd": "End",
    "Nav.SelectEnd": "Shift+End",
    "Nav.MoveDocStart": "Ctrl+Home",
    "Nav.SelectDocStart": "Ctrl+Shift+Home",
    "Nav.MoveDocEnd": "Ctrl+End",
    "Nav.SelectDocEnd": "Ctrl+Shift+End",
    "Nav.PageUp": "PageUp",
    "Nav.SelectPageUp": "Shift+PageUp",
    "Nav.PageDown": "PageDown",
    "Nav.SelectPageDown": "Shift+PageDown",
    "Nav.ColumnSelectUp": "Alt+Shift+Up",
    "Nav.ColumnSelectDown": "Alt+Shift+Down",
    "Nav.ColumnSelectLeft": "Alt+Shift+Left",
    "Nav.ColumnSelectRight": "Alt+Shift+Right",
    "Window.NextTab": "Ctrl+Tab",
    "Window.PrevTab": "Ctrl+Shift+Tab",
    "Window.Settings": "",
    "Search.CommandPalette": "F1",
    "Menu.File": "",
    "Menu.Edit": "",
    "Menu.Search": "",
    "Menu.View": "",
    "Menu.Help": ""
  },
  "bindings2": {
    "Nav.MoveLeft": "Ctrl+B",
    "Nav.MoveRight": "Ctrl+F",
    "Nav.MoveUp": "Ctrl+P",
    "Nav.MoveDown": "Ctrl+N",
    "Nav.MoveHome": "Ctrl+A",
    "Nav.MoveEnd": "Ctrl+E",
    "Nav.MoveWordLeft": "Alt+B",
    "Nav.MoveWordRight": "Alt+F",
    "Nav.PageUp": "Alt+V",
    "Nav.PageDown": "Ctrl+V",
    "Edit.Delete": "Ctrl+D",
    "Edit.UpperCase": "Alt+U",
    "Edit.LowerCase": "Alt+L",
    "Edit.ProperCase": "Alt+C"
  }
}
